django_pods-1.1.4.dist-info/DESCRIPTION.rst
django_pods-1.1.4.dist-info/METADATA
django_pods-1.1.4.dist-info/RECORD
django_pods-1.1.4.dist-info/WHEEL
django_pods-1.1.4.dist-info/metadata.json
django_pods-1.1.4.dist-info/top_level.txt
pods/__init__.py
pods/apps.py
