Metadata-Version: 2.0
Name: django-pods
Version: 1.1.4
Summary: App Settings for Django
Home-page: https://github.com/jthi3rry/django-pods
Author: Thierry Jossermoz
Author-email: thierry.jossermoz@oohlalabs.com
License: MIT
Platform: UNKNOWN
Classifier: Development Status :: 5 - Production/Stable
Classifier: Environment :: Web Environment
Classifier: Intended Audience :: Developers
Classifier: Operating System :: OS Independent
Classifier: Programming Language :: Python
Classifier: Programming Language :: Python :: 2.7
Classifier: Programming Language :: Python :: 3.5
Classifier: Programming Language :: Python :: 3.6
Classifier: Topic :: Software Development :: Libraries :: Python Modules
Classifier: Framework :: Django
Requires-Dist: Django
